[
  {
    "bigvideo_href": "/article/6758971053805928971",
    "bigvideo_title": "百万级宾利欧陆GT竟是水货 一罐清洗剂还原真实身份",
    "bigvideo_imageUrl": "https://p7.pstatp.com/large/bef700007260592c6cdc",
    "smallvideo": [
      {
        "smallvideo_href": "/article/6759144759266116110",
        "smallvideo_title": "新国产高端品牌，星途LX的明星之路可有实力依仗？懂车评测全面看",
        "smallvideo_imageUrl": "https://p7.pstatp.com/large/bef700007261a34051f8",
        "smallvideo_time": "15:53"
      },
      {
        "smallvideo_href": "/article/6759089118879154692",
        "smallvideo_title": "里程焦虑？不存在的！特斯拉MODEL 3带给你未来的出行方式",
        "smallvideo_imageUrl": "https://p3.pstatp.com/large/1767600001cfe1d0f446d",
        "smallvideo_time": "25:58"
      },
      {
        "smallvideo_href": "/article/6758624685040075277",
        "smallvideo_title": "3.7秒破百，起步打爆GTR的TTRS能教超跑做人！",
        "smallvideo_imageUrl": "https://p3.pstatp.com/large/1767400007178815df1de",
        "smallvideo_time": "11:26"
      },
      {
        "smallvideo_href": "/article/6758423004427862541",
        "smallvideo_title": "《热血车匠》第2集：溜溜哥盲盒选择遭翻盘，决战开启拉力定输赢",
        "smallvideo_imageUrl": "https://p7.pstatp.com/large/bef70000725c94468f04",
        "smallvideo_time": "44:53"
      },
      {
        "smallvideo_href": "/article/6758305570828059149",
        "smallvideo_title": "你第一次开车是什么时候？",
        "smallvideo_imageUrl": "https://p7.pstatp.com/large/176750000702cf2fee5c3",
        "smallvideo_time": "07:37"
      },
      {
        "smallvideo_href": "/article/6757993213706928648",
        "smallvideo_title": "雷克萨斯LC：超百万的豪华GT，看完你还买911吗？",
        "smallvideo_imageUrl": "https://p7.pstatp.com/large/bef80000725e6057205c",
        "smallvideo_time": "06:35"
      }
    ]
  },
  {
    "bigvideo_href": "/article/6758036180266140163",
    "bigvideo_title": "情怀不敌硬实力？背靠大众的捷达VS5是否德味儿依旧？",
    "bigvideo_imageUrl": "https://p7.pstatp.com/large/1767600001cf8ea782314",
    "smallvideo": [
      {
        "smallvideo_href": "/article/6757984385540030980",
        "smallvideo_title": "国6之后想“抄底”的人哭了，这辆丰田二手车和新车一个价！",
        "smallvideo_imageUrl": "https://p7.pstatp.com/large/bef80000725b675ec0f4",
        "smallvideo_time": "10:43"
      },
      {
        "smallvideo_href": "/article/6757639544071258631",
        "smallvideo_title": "38号车评中心 对比天籁vs雅阁vs亚洲龙",
        "smallvideo_imageUrl": "https://p7.pstatp.com/large/1767600001cf4790a6abe",
        "smallvideo_time": "19:38"
      },
      {
        "smallvideo_href": "/article/6756476112290710019",
        "smallvideo_title": "不是相声！教你把2.0T改到1000匹",
        "smallvideo_imageUrl": "https://p7.pstatp.com/large/bef800007251641939d9",
        "smallvideo_time": "11:35"
      },
      {
        "smallvideo_href": "/article/6756400203365876235",
        "smallvideo_title": "限行日开车有“绝招” 谁知交警半夜已在楼下车前",
        "smallvideo_imageUrl": "https://p2.pstatp.com/large/176750000701daef0c8d7",
        "smallvideo_time": "03:04"
      },
      {
        "smallvideo_href": "/article/6756089054460117508",
        "smallvideo_title": "旧神已死，新神已立？不！小马哥告诉你拉法仍是当代神车！",
        "smallvideo_imageUrl": "https://p7.pstatp.com/large/bef800007250a38bda7a",
        "smallvideo_time": "12:01"
      },
      {
        "smallvideo_href": "/article/6756092594117165571",
        "smallvideo_title": "10万就能买到大众神车，1.2T大众高尔夫，性价比碾压同级别所有车",
        "smallvideo_imageUrl": "https://p3.pstatp.com/large/bef50000ccf895c8b83e",
        "smallvideo_time": "09:06"
      }
    ]
  },
  {
    "bigvideo_href": "/article/6755690613158445576",
    "bigvideo_title": "各大厂商最顶尖的车子都在哪呢？",
    "bigvideo_imageUrl": "https://p7.pstatp.com/large/176750000701b622b41ed",
    "smallvideo": [
      {
        "smallvideo_href": "/article/6755074735735849486",
        "smallvideo_title": "六缸“凯美瑞”身价60万",
        "smallvideo_imageUrl": "https://p7.pstatp.com/large/bef600007358f663557b",
        "smallvideo_time": "09:44"
      },
      {
        "smallvideo_href": "/article/6755674951824458244",
        "smallvideo_title": "换代前最后一次改款，上市五年的C级还能不能打？",
        "smallvideo_imageUrl": "https://p7.pstatp.com/large/bef6000073572249b645",
        "smallvideo_time": "16:49"
      },
      {
        "smallvideo_href": "/article/6755382773826978315",
        "smallvideo_title": "酷炫双门不是绝对，帅气又实用A5 Sportback才是小姐姐们的真爱！",
        "smallvideo_imageUrl": "https://p7.pstatp.com/large/bef80000724cb561789c",
        "smallvideo_time": "12:20"
      },
      {
        "smallvideo_href": "/article/6755035807020483076",
        "smallvideo_title": "38号车评中心 详细测试全新一代日产天籁",
        "smallvideo_imageUrl": "https://p7.pstatp.com/large/bef50000ccf4c0c687da",
        "smallvideo_time": "18:14"
      },
      {
        "smallvideo_href": "/article/6755073241032688136",
        "smallvideo_title": "自主头等舱迈克萨斯G20，全面PK合资公务舱GL8！差价10万谁更值",
        "smallvideo_imageUrl": "https://p3.pstatp.com/large/bef50000ccf3d1e32e49",
        "smallvideo_time": "18:37"
      },
      {
        "smallvideo_href": "/article/6754550667001463303",
        "smallvideo_title": "Source丨说起本田思域，你是喜欢type R还是只剩半截VTEC的Si？",
        "smallvideo_imageUrl": "https://p3.pstatp.com/large/176750000701940bcc977",
        "smallvideo_time": "06:02"
      }
    ]
  }
]